README.md
setup.py
myfunniest/__init__.py
myfunniest/exception.py
myfunniest/meta.py
myfunniest/mytest.py
myfunniest/power_cache_client.py
myfunniest.egg-info/PKG-INFO
myfunniest.egg-info/SOURCES.txt
myfunniest.egg-info/dependency_links.txt
myfunniest.egg-info/not-zip-safe
myfunniest.egg-info/top_level.txt