Metadata-Version: 1.0
Name: myfunniest
Version: 0.13
Summary: The funniest joke in the world,this is new test
Home-page: http://github.com/storborg/funniest
Author: liguilin
Author-email: liguilin@zhongan.com
License: MIT
Platform: UNKNOWN
